eclipse/__init__.py
eclipse/bpe_simple_vocab_16e6.txt.gz
eclipse/clip.py
eclipse/model.py
eclipse/simple_tokenizer.py
eclipse-0.3.1.dist-info/LICENSE.md
eclipse-0.3.1.dist-info/WHEEL
eclipse-0.3.1.dist-info/METADATA
eclipse-0.3.1.dist-info/RECORD
