Metadata-Version: 2.1
Name: eclipse
Version: 0.3.1
Summary: A simplified and extended version of OpenAI's Contrastive Language-Image Pretraining
License: CC0 1.0 Universal
Author: CWDT
Author-email: null@cwdt.us
Requires-Python: >=3.6,<4.0
Classifier: License :: Other/Proprietary License
Classifier: Programming Language :: Python :: 3
Classifier: Programming Language :: Python :: 3.6
Classifier: Programming Language :: Python :: 3.7
Classifier: Programming Language :: Python :: 3.8
Classifier: Programming Language :: Python :: 3.9
Requires-Dist: ftfy (>=6.0.3,<7.0.0)
Requires-Dist: pandas (>=1.0.0,<2.0.0)
Requires-Dist: regex (>=2021.11.10,<2022.0.0)
Requires-Dist: torch (>=1.7.1,<2.0.0)
Requires-Dist: torchvision (>=0.11.1,<0.12.0)
Requires-Dist: tqdm (>=4.62.3,<5.0.0)
